{
  "5080|APCY-E": {
    "id": "1Uai6PoojYjXifkhZp9xhZYdVcesNF675",
    "name": "APCY5080DEYR4_114.8F.pdf"
  },
  "5085|APCY-E": {
    "id": "1OX42lIAci5BA4TgjH65AF5YNoEby61KJ",
    "name": "APCY5085DEYR4_114.8F.pdf"
  },
  "5090|APCY-E": {
    "id": "1H6xQX5u0kHPnV5D-TXNKG7AQl5WNNGWv",
    "name": "APCY5090DEYR4_114.8F.pdf"
  },
  "5095|APCY-E": {
    "id": "1lWvGRp6ATmdbZbbuSqc8BMKYp0SLK1o5",
    "name": "APCY5095DEYR4_114.8F.pdf"
  },
  "5105|APCY-E": {
    "id": "1EYoi7bXqfZRT20N0BF8Oi_a7tmCRxvXA",
    "name": "APCY5105DEYR4_114.8F.pdf"
  },
  "5115|APCY-E": {
    "id": "14JfCZZSgFeVqkk1tlBsa4sY2Q1DYQTB1",
    "name": "APCY5115DEYR4_114.8F.pdf"
  },
  "5125|APCY-E": {
    "id": "1N2Lp46mlmWAMEgBfEvNcFjzo6dthzUb1",
    "name": "APCY5125DEYR4_114.8F.pdf"
  },
  "5130|APCY-E": {
    "id": "1f20aljkQa-SkWT-wHPJY_wyZgmpXvU6k",
    "name": "APCY5130DEYR4_114.8F.pdf"
  },
  "5140|APCY-E": {
    "id": "1PdArccxTwVbB2e9ZRDatLAHTEjc8GrwS",
    "name": "APCY5140DEYR4_114.8F.pdf"
  },
  "5155|APCY-E": {
    "id": "1R2NHMU9ukJtFVF9LgN6ZW1qOyf957TJw",
    "name": "APCY5155DEYR4_114.8F.pdf"
  },
  "5165|APCY-E": {
    "id": "1biiFpJ2-0pr2KEgNJ314Ou-NLsLdOf6g",
    "name": "APCY5165DEYR4_114.8F.pdf"
  },
  "5175|APCY-E": {
    "id": "1DkSkU4W09k7u4sM6DdcCqxLJcFmafudG",
    "name": "APCY5175DEYR4_114.8F.pdf"
  },
  "5185|APCY-E": {
    "id": "1bYTZhmIpbORq-kGP9REssWpyH4pCJsHX",
    "name": "APCY5185DEYR4_114.8F.pdf"
  },
  "5195|APCY-E": {
    "id": "1Bn-TWTPlXgKW2SQB4mkfjEMt0fQbOxS2",
    "name": "APCY5195DEYR4_114.8F.pdf"
  },
  "5210|APCY-E": {
    "id": "1ImK1epE5bmKX66i1Fuc0GdCw-rKX-8r4",
    "name": "APCY5210DEYR4_114.8F.pdf"
  },
  "5230|APCY-E": {
    "id": "16nX4t4WGE7PzWX8t9gbP4PkpZSjfx3H5",
    "name": "APCY5230DEYR4_114.8F.pdf"
  },
  "5250|APCY-E": {
    "id": "1ZB6aESsm43pSAMu3BZpgto8klWcJsHg5",
    "name": "APCY5250DEYR4_114.8F.pdf"
  },
  "5265|APCY-E": {
    "id": "1ScaYabu_Lwmf8hOxMBWQvg4tNhUuZvy9",
    "name": "APCY5265DEYR4_114.8F.pdf"
  },
  "5285|APCY-E": {
    "id": "128xLextK2O6vws_xpOMq8y5zMV-7IJ9I",
    "name": "APCY5285DEYR4_114.8F.pdf"
  },
  "5300|APCY-E": {
    "id": "1iU-BM6L5QW7wVwXefVj2pxhoPjflr1Up",
    "name": "APCY5300DEYR4_114.8F.pdf"
  },
  "5325|APCY-E": {
    "id": "1tl_Jt4TbYAngYDR9CInvesFP8E8mVBpZ",
    "name": "APCY5325DEYR4_114.8F.pdf"
  },
  "5345|APCY-E": {
    "id": "1WmWhjsHMTKzzOSx9DkLacJLu4s7h5_xH",
    "name": "APCY5345DEYR4_114.8F.pdf"
  },
  "5365|APCY-E": {
    "id": "1xBGT9e9ckyxXLQuQMS1OtYQGBoVxYm3V",
    "name": "APCY5365TEYR4_114.8F.pdf"
  },
  "5380|APCY-E": {
    "id": "1-Ky8UrXp_77WV64ylSYlLV7dejBYkQAC",
    "name": "APCY5380TEYR4_114.8F.pdf"
  },
  "5395|APCY-E": {
    "id": "18nTxN1-HVDVZ_715qlc35SCliO8Fs_Es",
    "name": "APCY5395TEYR4_114.8F.pdf"
  },
  "5410|APCY-E": {
    "id": "1DaK_wskE2UP1qpNzYMZaYh1Nei5gYxog",
    "name": "APCY5410TEYR4_114.8F.pdf"
  },
  "5425|APCY-E": {
    "id": "109ZZJekGHd07stALq-nNqyTlzXLGXys7",
    "name": "APCY5425TEYR4_114.8F.pdf"
  },
  "5080|APCY-H": {
    "id": "1rQM4KVjt3nKjMY2nKsCGqhpc22YYWe6i",
    "name": "APCY5080DHYR7_114.8F.pdf"
  },
  "5085|APCY-H": {
    "id": "1GmcR8r6r2P2mrdA8icFJectXwLHmGjH2",
    "name": "APCY5085DHYR7_114.8F.pdf"
  },
  "5090|APCY-H": {
    "id": "1o7ip0tnOLcfjkV8j8a4JWzBjoQOTwth9",
    "name": "APCY5090DHYR7_114.8F.pdf"
  },
  "5095|APCY-H": {
    "id": "12f8nH9QNakSB5OAK6DxW9RWxdN-Cqu4P",
    "name": "APCY5095DHYR7_114.8F.pdf"
  },
  "5105|APCY-H": {
    "id": "1wmBgmRqGeBa3_ozyK20BsQNSHzhGFn__",
    "name": "APCY5105DHYR7_114.8F.pdf"
  },
  "5115|APCY-H": {
    "id": "1JfKf5F1FQw01pV1wf5iT5EdAkYhLvBR-",
    "name": "APCY5115DHYR7_114.8F.pdf"
  },
  "5125|APCY-H": {
    "id": "1iOJEBb-G8BOW4dh4rBVeA8wv92a0Vf6N",
    "name": "APCY5125DHYR7_114.8F.pdf"
  },
  "5130|APCY-H": {
    "id": "10rRG2HFR3BLugCrWs9vSdv2dRE3kliy5",
    "name": "APCY5130DHYR7_114.8F.pdf"
  },
  "5140|APCY-H": {
    "id": "1iXdzY6CUenZ96TXyQsdaJbtF3bc4pYJB",
    "name": "APCY5140DHYR7_114.8F.pdf"
  },
  "5155|APCY-H": {
    "id": "1hsVGGWU-EVgA8Ce1M2-AAFieL4E42jEQ",
    "name": "APCY5155DHYR7_114.8F.pdf"
  },
  "5165|APCY-H": {
    "id": "1BesXvgTWveiuDayx-31_L_ekagWPFb3v",
    "name": "APCY5165DHYR7_114.8F.pdf"
  },
  "5175|APCY-H": {
    "id": "1fGUcl8C3Yd5-P95MqufPpWNEzdTYuCYo",
    "name": "APCY5175DHYR7_114.8F.pdf"
  },
  "5185|APCY-H": {
    "id": "17ki_DlF7YaHdfR_g5s43mSE_TQYCWLb6",
    "name": "APCY5185DHYR7_114.8F.pdf"
  },
  "5195|APCY-H": {
    "id": "1feKJMVewYd2C2QFMUaRMg9KWCmYBtZlZ",
    "name": "APCY5195DHYR7_114.8F.pdf"
  },
  "5210|APCY-H": {
    "id": "1bbAWmN7ysLmTPaUYmGH9ZsbmzkaJHJSf",
    "name": "APCY5210DHYR7_114.8F.pdf"
  },
  "5230|APCY-H": {
    "id": "185mFsbbD2fooT3QZHtZj6zDSeW3Zr1wN",
    "name": "APCY5230DHYR7_114.8F.pdf"
  },
  "5250|APCY-H": {
    "id": "1NzgOKefiq8-sIISIX2LftGwIVp7Jwab4",
    "name": "APCY5250DHYR7_114.8F.pdf"
  },
  "5265|APCY-H": {
    "id": "1c333DjA_LcJFYlkTHDP4sV3Y7izACBmc",
    "name": "APCY5265DHYR7_114.8F.pdf"
  },
  "5285|APCY-H": {
    "id": "1JM9QbB-WDUIdXK5_Wh7xFO43cZQ4oEj4",
    "name": "APCY5285DHYR7_114.8F.pdf"
  },
  "5300|APCY-H": {
    "id": "1uHE7nRTSAHqluDXMdEOvPBTCHgu_RyjZ",
    "name": "APCY5300DHYR7_114.8F.pdf"
  },
  "5325|APCY-H": {
    "id": "14wiFvZqAgMzsVde5hLSoQ8Q3OpKQ9mc1",
    "name": "APCY5325DHYR7_114.8F.pdf"
  },
  "5345|APCY-H": {
    "id": "1jsHhc4maZwvoDxsOh8IJzV6Tv-vyuDIe",
    "name": "APCY5345DHYR7_114.8F.pdf"
  },
  "5365|APCY-H": {
    "id": "1akFz6aGfU01vRgIPH6lWUEvrBV6r22_r",
    "name": "APCY5365THYR7_114.8F.pdf"
  },
  "5380|APCY-H": {
    "id": "1z-mHwBI-z6aZ0DnyVW_OIZ-Wvll4sr_v",
    "name": "APCY5380THYR7_114.8F.pdf"
  },
  "5395|APCY-H": {
    "id": "10EKYcRzxZJ5YAVLPi0Qe3qKX2Okj_2BC",
    "name": "APCY5395THYR7_114.8F.pdf"
  },
  "5410|APCY-H": {
    "id": "1bLpYulC9gWNLftsFV9jj4ql_vcxo00VH",
    "name": "APCY5410THYR7_114.8F.pdf"
  },
  "5425|APCY-H": {
    "id": "1GJAZn_Ob_vKaVmMXUI9MxMThMRVgLsdb",
    "name": "APCY5425THYR7_114.8F.pdf"
  },
  "5455|APCY-H": {
    "id": "1wAcqt1XrGR5XTcnbuX2t0pxaUSRO5oK_",
    "name": "APCY5455THYR7_114.8F.pdf"
  },
  "5475|APCY-H": {
    "id": "1l9C_5KYeAgX5NAcdaiHIXK8at0BAOhH7",
    "name": "APCY5475THYR7_114.8F.pdf"
  },
  "5495|APCY-H": {
    "id": "1x_Pt5IFA-_AhZ0UBpSUmkcjl517NECYR",
    "name": "APCY5495THYR7_114.8F.pdf"
  },
  "5520|APCY-H": {
    "id": "1cLSUMBJsLrCkx6FECcOoXq1FPxodymPe",
    "name": "APCY5520THYR7_114.8F.pdf"
  },
  "5530|APCY-H": {
    "id": "110x3cDczFp45K6nww9VTaLOEhbJXBzl5",
    "name": "APCY5530THYR7_114.8F.pdf"
  },
  "5540|APCY-H": {
    "id": "1ta6gHnmRRHOuDbx1toECSQKuAklUweKu",
    "name": "APCY5540QHYR7_114.8F.pdf"
  },
  "5550|APCY-H": {
    "id": "1FwEUgiCAXcRIRjh1nO3ck9s2Y0nj_gPZ",
    "name": "APCY5550QHYR7_114.8F.pdf"
  },
  "5560|APCY-H": {
    "id": "1ASq8TZuyirNxATGiOwWoMfqI_53ZHD__",
    "name": "APCY5560QHYR7_114.8F.pdf"
  },
  "5570|APCY-H": {
    "id": "1tQNY2G0GmJkKT24PXFzvCNts5Wra6Cn8",
    "name": "APCY5570QHYR7_114.8F.pdf"
  },
  "5590|APCY-H": {
    "id": "1lk1U-0E8vfuBhee8er5cnoha0sYiIUOy",
    "name": "APCY5590QHYR7_114.8F.pdf"
  },
  "5600|APCY-H": {
    "id": "1Nm-Nr2Io0bWvVl6b7KrgWJrAOFtcfovT",
    "name": "APCY5600QHYR7_114.8F.pdf"
  }
}